tamarix_analytics/__init__.py
tamarix_analytics/analytics.py
tamarix_analytics-0.0.7.dist-info/METADATA
tamarix_analytics-0.0.7.dist-info/WHEEL
tamarix_analytics-0.0.7.dist-info/top_level.txt
tamarix_analytics-0.0.7.dist-info/RECORD
