Metadata-Version: 2.2
Name: tamarix_analytics
Version: 0.0.7
Summary: A Python package for row matching and F1 score calculations.
Author: Tamarix Technologies
Author-email: kristian@tamarix.tech
Classifier: Programming Language :: Python :: 3
Classifier: License :: OSI Approved :: MIT License
Classifier: Operating System :: OS Independent
Requires-Python: >=3.8
Requires-Dist: munkres
Requires-Dist: pydantic
Dynamic: author
Dynamic: author-email
Dynamic: classifier
Dynamic: description
Dynamic: description-content-type
Dynamic: requires-dist
Dynamic: requires-python
Dynamic: summary
